{
  "meta": {
    "file_index": 49,
    "generated_at": "2024-09-03 23:49:52",
    "total_records": 13
  },
  "data": [
    {
      "id": 4900,
      "name": "Tina Wilson",
      "email": "tina.wilson@demo.net",
      "age": 20,
      "department": "HR",
      "city": "Taipei",
      "salary": 132463.18,
      "active": false,
      "joined": "2024-11-06",
      "skills": [
        "Kubernetes",
        "Java",
        "Rust",
        "Docker",
        "SQL"
      ]
    },
    {
      "id": 4901,
      "name": "Quinn Johnson",
      "email": "quinn.johnson@mail.io",
      "age": 23,
      "department": "Sales",
      "city": "Berlin",
      "salary": 93889.23,
      "active": false,
      "joined": "2020-01-22",
      "skills": [
        "Docker",
        "React",
        "Java",
        "Kubernetes",
        "Python"
      ]
    },
    {
      "id": 4902,
      "name": "Xander Davis",
      "email": "xander.davis@demo.net",
      "age": 24,
      "department": "Marketing",
      "city": "Singapore",
      "salary": 49737.79,
      "active": false,
      "joined": "2020-09-14",
      "skills": [
        "Python",
        "Rust"
      ]
    },
    {
      "id": 4903,
      "name": "Noah Smith",
      "email": "noah.smith@test.org",
      "age": 36,
      "department": "Marketing",
      "city": "Tokyo",
      "salary": 86829.18,
      "active": false,
      "joined": "2020-08-10",
      "skills": [
        "TypeScript",
        "Docker",
        "Java",
        "Go"
      ]
    },
    {
      "id": 4904,
      "name": "Tina Lewis",
      "email": "tina.lewis@demo.net",
      "age": 26,
      "department": "Operations",
      "city": "Paris",
      "salary": 99472.14,
      "active": true,
      "joined": "2020-09-05",
      "skills": [
        "Go",
        "React"
      ]
    },
    {
      "id": 4905,
      "name": "Wendy Williams",
      "email": "wendy.williams@mail.io",
      "age": 23,
      "department": "HR",
      "city": "Taipei",
      "salary": 66176.53,
      "active": false,
      "joined": "2020-09-26",
      "skills": [
        "Python",
        "TypeScript"
      ]
    },
    {
      "id": 4906,
      "name": "Bob Anderson",
      "email": "bob.anderson@demo.net",
      "age": 45,
      "department": "Engineering",
      "city": "Toronto",
      "salary": 120235.6,
      "active": true,
      "joined": "2020-02-13",
      "skills": [
        "Go",
        "Rust",
        "C++",
        "Kubernetes",
        "TypeScript"
      ]
    },
    {
      "id": 4907,
      "name": "Dave Taylor",
      "email": "dave.taylor@example.com",
      "age": 49,
      "department": "Finance",
      "city": "London",
      "salary": 100537.6,
      "active": true,
      "joined": "2021-02-24",
      "skills": [
        "C++",
        "Java"
      ]
    },
    {
      "id": 4908,
      "name": "Sam Miller",
      "email": "sam.miller@mail.io",
      "age": 60,
      "department": "Finance",
      "city": "New York",
      "salary": 72646.95,
      "active": false,
      "joined": "2024-12-26",
      "skills": [
        "Docker",
        "SQL",
        "Python"
      ]
    },
    {
      "id": 4909,
      "name": "Bob Jones",
      "email": "bob.jones@test.org",
      "age": 57,
      "department": "HR",
      "city": "Sydney",
      "salary": 145168.96,
      "active": false,
      "joined": "2023-06-28",
      "skills": [
        "SQL",
        "Rust",
        "Kubernetes"
      ]
    },
    {
      "id": 4910,
      "name": "Tina Taylor",
      "email": "tina.taylor@test.org",
      "age": 43,
      "department": "Engineering",
      "city": "Sydney",
      "salary": 100372.79,
      "active": true,
      "joined": "2020-08-22",
      "skills": [
        "TypeScript",
        "C++",
        "Python"
      ]
    },
    {
      "id": 4911,
      "name": "Noah Thomas",
      "email": "noah.thomas@mail.io",
      "age": 32,
      "department": "Operations",
      "city": "Singapore",
      "salary": 124231.66,
      "active": false,
      "joined": "2022-02-14",
      "skills": [
        "Rust",
        "React",
        "TypeScript",
        "Kubernetes",
        "SQL"
      ]
    },
    {
      "id": 4912,
      "name": "Noah Taylor",
      "email": "noah.taylor@mail.io",
      "age": 26,
      "department": "HR",
      "city": "Taipei",
      "salary": 89511.68,
      "active": true,
      "joined": "2022-07-02",
      "skills": [
        "Rust",
        "Docker",
        "TypeScript"
      ]
    }
  ]
}